lab08/ejercicio1/contador_modulos.v
module counter(input CLK, RESET, A, enable, input [11:0] LOAD, output reg [11:0] Y); 
	
	always @ (posedge CLK, posedge RESET, posedge A)
	
		if (RESET)  
			Y <= 0;
		else if (A)  
			Y <= LOAD;
		else if (enable)  
			Y <= Y + 1;
		else 
			Y <= Y; 
endmodule

lab08/ejercicio1/testbench_contador.v
`include "contador_modulos.v" 

module testbench();

	reg CLK, RESET, A, enable; 
	reg[11:0] LOAD; 
	wire[11:0] Y; 

	counter M1(CLK, RESET, A, enable, LOAD, Y) ; 

	initial begin 
	
		$display("A enable LOAD | Y"); 
		$monitor("%b %b %b | %b", A, enable, LOAD, Y); 
	end 
	
	initial begin 
		CLK = 0; RESET = 1; 
		#1 RESET = 0; enable = 1; A = 0; LOAD = 0; 
		#30 RESET = 0; enable = 1; A = 1; LOAD = 30;
		#31 RESET = 0; enable = 1; A = 0;
		#70 RESET = 0; enable = 0; A = 0;  
	end 
	
	initial 
	
	#500 $finish; 
	
	always 
		#2 CLK = ~CLK; 
	
	initial begin
        $dumpfile("contador_timing.vcd");
        $dumpvars(0, testbench);
    end
endmodule

lab08/ejercicio1/contador_timing.vcd
$date
	Sat Oct 24 23:28:25 2020
$end
$version
	Icarus Verilog
$end
$timescale
	1s
$end
$scope module testbench $end
$var wire 12 ! Y [11:0] $end
$var reg 1 " A $end
$var reg 1 # CLK $end
$var reg 12 $ LOAD [11:0] $end
$var reg 1 % RESET $end
$var reg 1 & enable $end
$scope module M1 $end
$var wire 1 " A $end
$var wire 1 # CLK $end
$var wire 12 ' LOAD [11:0] $end
$var wire 1 % RESET $end
$var wire 1 & enable $end
$var reg 12 ( Y [11:0] $end
$upscope $end
$upscope $end
$enddefinitions $end
#0
$dumpvars
b0 (
bx '
x&
1%
bx $
0#
x"
b0 !
$end
#1
b0 $
b0 '
0"
1&
0%
#2
b1 !
b1 (
1#
#4
0#
#6
b10 !
b10 (
1#
#8
0#
#10
b11 !
b11 (
1#
#12
0#
#14
b100 !
b100 (
1#
#16
0#
#18
b101 !
b101 (
1#
#20
0#
#22
b110 !
b110 (
1#
#24
0#
#26
b111 !
b111 (
1#
#28
0#
#30
b1000 !
b1000 (
1#
#31
b11110 !
b11110 (
b11110 $
b11110 '
1"
#32
0#
#34
1#
#36
0#
#38
1#
#40
0#
#42
1#
#44
0#
#46
1#
#48
0#
#50
1#
#52
0#
#54
1#
#56
0#
#58
1#
#60
0#
#62
b11111 !
b11111 (
1#
0"
#64
0#
#66
b100000 !
b100000 (
1#
#68
0#
#70
b100001 !
b100001 (
1#
#72
0#
#74
b100010 !
b100010 (
1#
#76
0#
#78
b100011 !
b100011 (
1#
#80
0#
#82
b100100 !
b100100 (
1#
#84
0#
#86
b100101 !
b100101 (
1#
#88
0#
#90
b100110 !
b100110 (
1#
#92
0#
#94
b100111 !
b100111 (
1#
#96
0#
#98
b101000 !
b101000 (
1#
#100
0#
#102
b101001 !
b101001 (
1#
#104
0#
#106
b101010 !
b101010 (
1#
#108
0#
#110
b101011 !
b101011 (
1#
#112
0#
#114
b101100 !
b101100 (
1#
#116
0#
#118
b101101 !
b101101 (
1#
#120
0#
#122
b101110 !
b101110 (
1#
#124
0#
#126
b101111 !
b101111 (
1#
#128
0#
#130
b110000 !
b110000 (
1#
#132
0#
0&
