proyectoFSM/FSM1/modulos_FSM1.v
module FFD (input clk, reset, D, output reg Q);

  always @ (posedge clk or posedge reset) begin
    if (reset)
      Q <= 1'b0;
    else
      Q <= D;
  end
endmodule

// Implementacion de la primer FSM 

module FSM1(input A, B, C, D, clk, reset, output wire M0, M1, S0, S1, S0F, S1F);

 // Cables de interconexiones
    wire M_0, M_1, S_0, S_1, S0_F, S1_F;    
	
    // Calculo del estado futuro de la FSM1
    assign S0_F = (S_1)&(A)&(~B)&(C)&(~D) | (~S_1)&(A)&(B)&(C)&(~D)| (S_0)&(~S_1)&(A)&(~B) | (S_0)&(S_1)&(A)&(B);
    assign S1_F = (~S_0)&(S_1)&(~A)&(B) | (~S_1)&(B)&(C)&(~D) | (S_0)&(S_1)&(A)&(B);
    // Calculo de salidas de la FSM1
    assign M0 = S_0;
	assign M1 = S_1; 
    
    FFD E0(clk, reset, S0_F, S_0);
    FFD E1(clk, reset, S1_F, S_1);
    
    // Visulizacion de los estados actulaes y futuros 
    assign S0 = S_0; 
	assign S1 = S_1; 
	assign S0F = S0_F;
    assign S1F = S1_F;

endmodule

proyectoFSM/FSM1/testbench_FSM1.v
`include "modulos_FSM1.v"  

module testbench();

	reg A, B, C, D, clk, reset; 
	wire M0, M1, S0, S1, S0F, S1F; 

	FSM1 U1(A, B, C, D, clk, reset, M0, M1, S0, S1, S0F, S1F); 
	
	initial begin 
		
		$display("A B C D S0 S1 S0F S1F | M0 M1"); 
		$monitor("%b %b %b %b %b %b %b %b| %b %b" , A, B, C, D, S0, S1, S0F, S1F, M0, M1); 
	end 
	
	initial begin 
		
		clk = 0; reset = 0; 
		#15 A=0; B=0; C=0; D=0; 
		#20 A=0; B=0; C=1; D=1; 
		#25 A=0; B=0; C=1; D=0; 
		#30 A=0; B=1; C=1; D=0; 
		#35 A=0; B=1; C=1; D=1;
		#40 A=0; B=1; C=1; D=0;
		#45 A=0; B=1; C=0; D=1;
		#50 A=0; B=1; C=1; D=0;
		#55 A=1; B=0; C=1; D=0; 
		#60 A=1; B=0; C=1; D=1;
		#65 A=1; B=0; C=1; D=0;
		#70 A=1; B=0; C=0; D=1;
		#75 A=1; B=0; C=1; D=0;
		#80 A=1; B=1; C=1; D=0; 
		#85 A=1; B=1; C=1; D=1;
		#90 A=1; B=1; C=1; D=0;
		#95 A=1; B=1; C=0; D=1;
		#100 A=1; B=1; C=1; D=0;
		#105 A=0; B=0; C=1; D=0;
		#110 A=1; B=1; C=1; D=0;
		#115 A=1; B=0; C=1; D=0;
		#120 A=0; B=1; C=1; D=0;
		#125 A=0; B=0; C=1; D=0;
	end 
	
	initial 
	
	#500 $finish; 
	
	always 
		#7 clk = ~clk; 
	
	initial begin
        $dumpfile("FSM1_timing.vcd");
        $dumpvars(0, testbench);
    end
endmodule

proyectoFSM/FSM1/FSM1_timing.vcd
$date
	Sat Oct 17 22:50:39 2020
$end
$version
	Icarus Verilog
$end
$timescale
	1s
$end
$scope module testbench $end
$var wire 1 ! S1F $end
$var wire 1 " S1 $end
$var wire 1 # S0F $end
$var wire 1 $ S0 $end
$var wire 1 % M1 $end
$var wire 1 & M0 $end
$var reg 1 ' A $end
$var reg 1 ( B $end
$var reg 1 ) C $end
$var reg 1 * D $end
$var reg 1 + clk $end
$var reg 1 , reset $end
$scope module U1 $end
$var wire 1 ' A $end
$var wire 1 ( B $end
$var wire 1 ) C $end
$var wire 1 * D $end
$var wire 1 & M0 $end
$var wire 1 % M1 $end
$var wire 1 $ S0 $end
$var wire 1 # S0F $end
$var wire 1 - S0_F $end
$var wire 1 " S1 $end
$var wire 1 ! S1F $end
$var wire 1 . S1_F $end
$var wire 1 + clk $end
$var wire 1 , reset $end
$var wire 1 / S_1 $end
$var wire 1 0 S_0 $end
$scope module E0 $end
$var wire 1 - D $end
$var wire 1 + clk $end
$var wire 1 , reset $end
$var reg 1 0 Q $end
$upscope $end
$scope module E1 $end
$var wire 1 . D $end
$var wire 1 + clk $end
$var wire 1 , reset $end
$var reg 1 / Q $end
$upscope $end
$upscope $end
$upscope $end
$enddefinitions $end
#0
$dumpvars
x0
x/
x.
x-
0,
0+
x*
x)
x(
x'
x&
x%
x$
x#
x"
x!
$end
#7
1+
#14
0+
#15
0#
0-
0!
0.
0*
0)
0(
0'
#21
0"
0%
0/
0$
0&
00
1+
#28
0+
#35
1+
1*
1)
#42
0+
#49
1+
#56
0+
#60
0*
#63
1+
#70
0+
#77
1+
#84
0+
#90
1!
1.
1(
#91
1"
1%
1/
1+
#98
0+
#105
1+
#112
0+
#119
1+
#125
1*
#126
0+
#133
1+
#140
0+
#147
1+
#154
0+
#161
1+
#165
0*
#168
0+
#175
1+
#182
0+
#189
1+
#196
0+
#203
1+
#210
0+
1*
0)
#217
1+
#224
0+
#231
1+
#238
0+
#245
1+
#252
0+
#259
1+
#260
0*
1)
#266
0+
#273
1+
#280
0+
#287
1+
#294
0+
#301
1+
#308
0+
#315
1#
1-
0!
0.
1+
0(
1'
#322
0+
#329
0"
0%
0/
1$
1&
10
1+
#336
0+
#343
1+
#350
0+
#357
1+
#364
0+
#371
1+
#375
1*
#378
0+
#385
1+
#392
0+
#399
1+
#406
0+
#413
1+
#420
0+
#427
1+
#434
0+
#440
0*
