lab03/tabla01_POS/codigoPOStabla1.v
module pruenbaPOStabla1();
	wire w01,w02,w03,w1,w2,w3,out;
	reg A,B,C;
	not n1(w01,A);
	not n2(w02,B);
	not n3(w03,C);
	
	or e1(w1,A,B,w03);
	or e2(w2,A,w02,w03);
	or e3(w3,w01,w02,C);
	and s1(out,w1,w2,w3);
	
	initial begin 
		$display("A B C | Y");
		$display("------|--");
		$monitor("%b %b %b | %b" , A,B,C,out);
		A=0; B=0; C=0; 
		#1 A=0; B=0; C=1;
		#1 A=0; B=1; C=0;
		#1 A=0; B=1; C=1;
		#1 A=1; B=0; C=0;
		#1 A=1; B=0; C=1;
		#1 A=1; B=1; C=0;
		#1 A=1; B=1; C=1;
		#1 $finish;
	end 
	
	initial begin 
		$dumpfile("codigoPOStabla1_tb.vcd");
		$dumpvars(0,pruenbaPOStabla1);
	end 

endmodule

lab03/tabla01_POS/codigoPOStabla1_tb.vcd
$date
	Sat Aug 08 09:17:50 2020
$end
$version
	Icarus Verilog
$end
$timescale
	1s
$end
$scope module pruenbaPOStabla1 $end
$var wire 1 ! out $end
$var wire 1 " w01 $end
$var wire 1 # w02 $end
$var wire 1 $ w03 $end
$var wire 1 % w1 $end
$var wire 1 & w2 $end
$var wire 1 ' w3 $end
$var reg 1 ( A $end
$var reg 1 ) B $end
$var reg 1 * C $end
$upscope $end
$enddefinitions $end
#0
$dumpvars
0*
0)
0(
1'
1&
1%
1$
1#
1"
1!
$end
#1
0!
0%
0$
1*
#2
1!
1$
1%
0#
0*
1)
#3
0!
0&
0$
1*
#4
1!
1$
1#
1&
0"
0*
0)
1(
#5
0$
1*
#6
0!
0'
1$
0#
0*
1)
#7
1!
1'
0$
1*
