lab04/ejercicio 5/ProblemaAlarma.v
// ecuaciones de ejercicio 05 
// tipo de solucion por gate level 

// Ecuacion SOP  

module t01(input wire A, B , C , output wire Y); 

	wire notB, notC, w1, w2, w3; 
	not (notB, B); 
	not (notC, C); 
	and(w1, A, notB, C); 
	and(w2, A, B, notC); 
	and(w3, A, B, C); 
	or(Y, w1,w2,w3); 

endmodule 

// Ecuacion POS 

module t02(input wire A, B , C , output wire Y); 

	wire notA, notB, notC, w1, w2, w3, w4, w5; 
	not (notA, A); 
	not (notB, B); 
	not (notC, C); 
	or (w1, A, B, C); 
	or (w2, A, B, notC); 
	or (w3, A, notB, C); 
	or (w4, A, notB, notC); 
	or (w5, notA, B, C); 
	and (Y, w1,w2,w3,w4,w5);

endmodule 

// Ecuacion minimizada

module t03(input wire A, B , C , output wire Y); 

	wire w1, w2; 
	and (w1, A, B); 
	and (w2, A, C); 
	or (Y, w1,w2);

endmodule 

// ecuaciones de ejercicio 5
// tipo de solucion por operadores logicos 


// Ecuacion SOP  

module f01(input wire A, B, C, output wire Y); 

	assign Y = (A & ~B & C) | (A & B & ~C) | (A & B & C) ; 
	
endmodule 

// Ecuacion POS 

module f02(input wire A, B, C, output wire Y);

	assign Y = (A | B | C)&(A | B | ~C)&(A | ~B | C)&(A | ~B | ~C)&(~A | B | C) ; 
	
endmodule 

// Ecuacion minimizada

module f03(input wire A, B, C, output wire Y);

	assign Y = (A & B) | (A & C) ;

endmodule

lab04/ejercicio 5/ProblemaAlarma_tb.v
`include "ProblemaAlarma.v" 

module testbench();

	reg a1, a2, a3;
	reg b1, b2, b3; 
	reg c1, c2, c3; 
	reg d1, d2, d3; 
	reg e1, e2, e3; 
	reg f1, f2, f3; 
	wire s1, s2, s3, s4, s5, s6; 
	
	t01 m1(a1,a2,a3,s1); 
	t02 m2(b1,b2,b3,s2);
	t03 m3(c1,c2,c3,s3); 
	f01 n1(d1,d2,d3,s4);
	f02 n2(e1,e2,e3,s5);
	f03 n3(f1,f2,f3,s6);
	
	initial begin 
		$display("ecuaciones con gate level ");
		$display("\n");
		$display("ecuacion SOP");
		$display("A B C | Y ");
		$display("------|------");
		$monitor("%b %b %b | %b", a1, a2, a3, s1);
		a1 = 0; a2 = 0; a3 = 0;
		#1 a1 = 0; a2 = 0; a3 = 1;
		#1 a1 = 0; a2 = 1; a3 = 0;
		#1 a1 = 0; a2 = 1; a3 = 1;
		#1 a1 = 1; a2 = 0; a3 = 0;
		#1 a1 = 1; a2 = 0; a3 = 1;
		#1 a1 = 1; a2 = 1; a3 = 0;
		#1 a1 = 1; a2 = 1; a3 = 1;
	end 
	
	initial begin 
		#10 
		$display("\n");
		$display("ecuacion POS");
		$display("A B C | Y");
		$display("------|--");
		$monitor("%b %b %b | %b", b1, b2, b3, s2);
		b1 = 0; b2 = 0; b3 = 0;
		#1 b1 = 0; b2 = 0; b3 = 1;
		#1 b1 = 0; b2 = 1; b3 = 0;
		#1 b1 = 0; b2 = 1; b3 = 1;
		#1 b1 = 1; b2 = 0; b3 = 0;
		#1 b1 = 1; b2 = 0; b3 = 1;
		#1 b1 = 1; b2 = 1; b3 = 0;
		#1 b1 = 1; b2 = 1; b3 = 1;
	end 
	
	initial begin 
		#19 
		$display("\n");
		$display("ecuacion minimizada");
		$display("A B C | Y");
		$display("--------|--");
		$monitor("%b %b %b | %b" , c1,c2,c3,s3);
		c1=0; c2=0; c3=0; 
		#1 c1 = 0; c2 = 0; c3 = 1;
		#1 c1 = 0; c2 = 1; c3 = 0;
		#1 c1 = 0; c2 = 1; c3 = 1;
		#1 c1 = 1; c2 = 0; c3 = 0;
		#1 c1 = 1; c2 = 0; c3 = 1;
		#1 c1 = 1; c2 = 1; c3 = 0;
		#1 c1 = 1; c2 = 1; c3 = 1;
	end 
	
	initial begin 
		#28
		$display("\n");
		$display("ecuaciones con operadores logicos");
		$display("\n");
		$display("ecuacion SOP");
		$display("A B C | Y");
		$display("--------|--");
		$monitor("%b %b %b | %b" , d1,d2,d3,s4);
		d1=0; d2=0; d3=0; 
		#1 d1 = 0; d2 = 0; d3 = 1;
		#1 d1 = 0; d2 = 1; d3 = 0;
		#1 d1 = 0; d2 = 1; d3 = 1;
		#1 d1 = 1; d2 = 0; d3 = 0;
		#1 d1 = 1; d2 = 0; d3 = 1;
		#1 d1 = 1; d2 = 1; d3 = 0;
		#1 d1 = 1; d2 = 1; d3 = 1;
	end 
	
	initial begin 
		#37
		$display("\n");
		$display("ecuacion POS");
		$display("A B C | Y");
		$display("--------|--");
		$monitor("%b %b %b | %b" , e1,e2,e3,s5);
		e1=0; e2=0; e3=0; 
		#1 e1 = 0; e2 = 0; e3 = 1;
		#1 e1 = 0; e2 = 1; e3 = 0;
		#1 e1 = 0; e2 = 1; e3 = 1;
		#1 e1 = 1; e2 = 0; e3 = 0;
		#1 e1 = 1; e2 = 0; e3 = 1;
		#1 e1 = 1; e2 = 1; e3 = 0;
		#1 e1 = 1; e2 = 1; e3 = 1;
	end 
	
	initial begin 
		#46
		$display("\n");
		$display("ecuacion minimizada");
		$display("A B C | Y");
		$display("------|--");
		$monitor("%b %b %b | %b", f1, f2, f3, s6);
		f1 = 0; f2 = 0; f3 = 0;
		#1 f1 = 0; f2 = 0; f3 = 1;
		#1 f1 = 0; f2 = 1; f3 = 0;
		#1 f1 = 0; f2 = 1; f3 = 1;
		#1 f1 = 1; f2 = 0; f3 = 0;
		#1 f1 = 1; f2 = 0; f3 = 1;
		#1 f1 = 1; f2 = 1; f3 = 0;
		#1 f1 = 1; f2 = 1; f3 = 1;
	end 
	
	initial 
		#55 $finish; 
	
	initial begin 
		$dumpfile("ProblemaAlarma_tb.vcd");
		$dumpvars(0, testbench);
	end 

endmodule

lab04/ejercicio 5/ProblemaAlarma_tb.vcd
$date
	Sun Aug 09 23:20:38 2020
$end
$version
	Icarus Verilog
$end
$timescale
	1s
$end
$scope module testbench $end
$var wire 1 ! s6 $end
$var wire 1 " s5 $end
$var wire 1 # s4 $end
$var wire 1 $ s3 $end
$var wire 1 % s2 $end
$var wire 1 & s1 $end
$var reg 1 ' a1 $end
$var reg 1 ( a2 $end
$var reg 1 ) a3 $end
$var reg 1 * b1 $end
$var reg 1 + b2 $end
$var reg 1 , b3 $end
$var reg 1 - c1 $end
$var reg 1 . c2 $end
$var reg 1 / c3 $end
$var reg 1 0 d1 $end
$var reg 1 1 d2 $end
$var reg 1 2 d3 $end
$var reg 1 3 e1 $end
$var reg 1 4 e2 $end
$var reg 1 5 e3 $end
$var reg 1 6 f1 $end
$var reg 1 7 f2 $end
$var reg 1 8 f3 $end
$scope module m1 $end
$var wire 1 ' A $end
$var wire 1 ( B $end
$var wire 1 ) C $end
$var wire 1 & Y $end
$var wire 1 9 notB $end
$var wire 1 : notC $end
$var wire 1 ; w1 $end
$var wire 1 < w2 $end
$var wire 1 = w3 $end
$upscope $end
$scope module m2 $end
$var wire 1 * A $end
$var wire 1 + B $end
$var wire 1 , C $end
$var wire 1 % Y $end
$var wire 1 > notA $end
$var wire 1 ? notB $end
$var wire 1 @ notC $end
$var wire 1 A w1 $end
$var wire 1 B w2 $end
$var wire 1 C w3 $end
$var wire 1 D w4 $end
$var wire 1 E w5 $end
$upscope $end
$scope module m3 $end
$var wire 1 - A $end
$var wire 1 . B $end
$var wire 1 / C $end
$var wire 1 $ Y $end
$var wire 1 F w1 $end
$var wire 1 G w2 $end
$upscope $end
$scope module n1 $end
$var wire 1 0 A $end
$var wire 1 1 B $end
$var wire 1 2 C $end
$var wire 1 # Y $end
$upscope $end
$scope module n2 $end
$var wire 1 3 A $end
$var wire 1 4 B $end
$var wire 1 5 C $end
$var wire 1 " Y $end
$upscope $end
$scope module n3 $end
$var wire 1 6 A $end
$var wire 1 7 B $end
$var wire 1 8 C $end
$var wire 1 ! Y $end
$upscope $end
$upscope $end
$enddefinitions $end
#0
$dumpvars
xG
xF
xE
xD
xC
xB
xA
x@
x?
x>
0=
0<
0;
1:
19
x8
x7
x6
x5
x4
x3
x2
x1
x0
x/
x.
x-
x,
x+
x*
0)
0(
0'
0&
x%
x$
x#
x"
x!
$end
#1
0:
1)
#2
1:
09
0)
1(
#3
0:
1)
#4
1:
19
0)
0(
1'
#5
1&
0:
1;
1)
#6
1<
1&
1:
0;
09
0)
1(
#7
0<
0:
1=
1)
#10
0%
1B
1C
1D
1@
1?
1E
1>
0A
0,
0+
0*
#11
0%
0B
0@
1A
1,
#12
1@
0C
0?
1B
0,
1+
#13
0%
0D
0@
1C
1,
#14
1@
1?
0E
0>
1D
0,
0+
1*
#15
1%
0@
1E
1,
#16
1@
0?
0,
1+
#17
0@
1,
#19
0$
0F
0G
0/
0.
0-
#20
1/
#21
0/
1.
#22
1/
#23
0/
0.
1-
#24
1$
1G
1/
#25
0G
1F
0/
1.
#26
1G
1/
#28
0#
02
01
00
#29
12
#30
02
11
#31
12
#32
02
01
10
#33
1#
12
#34
02
11
#35
12
#37
0"
05
04
03
#38
15
#39
05
14
#40
15
#41
05
04
13
#42
1"
15
#43
05
14
#44
15
#46
0!
08
07
06
#47
18
#48
08
17
#49
18
#50
08
07
16
#51
1!
18
#52
08
17
#53
18
