lab08/ejercicio3/ALU_modulo.v
module ALU(input [2:0] Caso, input [3:0] A, B, output wire [3:0] Y); 

	reg [3:0] C; 

	always @ (posedge Caso) 
	
		case(Caso) 
		
			3'b000:
				C = A & B; 
			3'b001: 
				C = A | B; 
			3'b010: 
				C = A + B; 
			3'b011: 
				C = 3'b000; 
			3'b100: 
				C = A & ~B; 
			3'b101: 
				C = A | ~B; 
			3'b110: 
				C = A - B; 
			3'b111: 
				C = (A < B) ? 1 : 0 ; 
		endcase
		
		assign Y = C; 
		
endmodule

lab08/ejercicio3/ALU_testbench.v
`include "ALU_modulo.v" 

module testbench();

	reg [2:0] caso; 
	reg [3:0] A, B; 
	wire [3:0] Y; 

	ALU M1(caso, A, B, Y); 
	
	initial begin 
		
		$display("CASO-----A-----B------ |  Y"); 
		$monitor("%b %b %b | %b", caso, A, B, Y); 
		
		caso = 3'b000; A = 4'b1001; B = 4'b1010; 
		#1 caso = 3'b001; A = 4'b1001; B = 4'b1010; 
		#1 caso = 3'b010; A = 4'b1001; B = 4'b1010; 
		#1 caso = 3'b011; A = 4'b1001; B = 4'b1010;  
		#1 caso = 3'b100; A = 4'b1001; B = 4'b1010; 
		#1 caso = 3'b101; A = 4'b1001; B = 4'b1010; 
		#1 caso = 3'b110; A = 4'b1001; B = 4'b1010;
		#1 caso = 3'b111; A = 4'b1001; B = 4'b1010; 
		
	end 
	
	initial 
	
	#50 $finish; 
	
	initial begin
        $dumpfile("ALU_timing.vcd");
        $dumpvars(0, testbench);
    end
endmodule

lab08/ejercicio3/ALU_timing.vcd
$date
	Sat Oct 24 23:20:15 2020
$end
$version
	Icarus Verilog
$end
$timescale
	1s
$end
$scope module testbench $end
$var wire 4 ! Y [3:0] $end
$var reg 4 " A [3:0] $end
$var reg 4 # B [3:0] $end
$var reg 3 $ caso [2:0] $end
$scope module M1 $end
$var wire 4 % A [3:0] $end
$var wire 4 & B [3:0] $end
$var wire 3 ' Caso [2:0] $end
$var wire 4 ( Y [3:0] $end
$var reg 4 ) C [3:0] $end
$upscope $end
$upscope $end
$enddefinitions $end
#0
$dumpvars
bx )
bx (
b0 '
b1010 &
b1001 %
b0 $
b1010 #
b1001 "
bx !
$end
#1
b1011 !
b1011 (
b1011 )
b1 $
b1 '
#2
b10 $
b10 '
#3
b0 !
b0 (
b0 )
b11 $
b11 '
#4
b100 $
b100 '
#5
b1101 !
b1101 (
b1101 )
b101 $
b101 '
#6
b110 $
b110 '
#7
b1 !
b1 (
b1 )
b111 $
b111 '
